cje/__init__.py
cje/__main__.py
cje/advanced.py
cje/calibration/README.md
cje/calibration/__init__.py
cje/calibration/dataset.py
cje/calibration/flexible_calibrator.py
cje/calibration/isotonic.py
cje/calibration/judge.py
cje/calibration/oracle_slice.py
cje/calibration/simcal.py
cje/conf/config.yaml
cje/conf/estimator/auto.yaml
cje/conf/estimator/calibrated-ips.yaml
cje/conf/estimator/dr-cpo.yaml
cje/conf/estimator/mrdr.yaml
cje/conf/estimator/raw-ips.yaml
cje/conf/estimator/stacked-dr.yaml
cje/conf/estimator/tmle.yaml
cje/data/README.md
cje/data/__init__.py
cje/data/factory.py
cje/data/folds.py
cje/data/fresh_draw_utils.py
cje/data/fresh_draws.py
cje/data/loaders.py
cje/data/models.py
cje/data/precomputed_sampler.py
cje/data/reward_utils.py
cje/data/validation.py
cje/diagnostics/README.md
cje/diagnostics/__init__.py
cje/diagnostics/display.py
cje/diagnostics/dr.py
cje/diagnostics/models.py
cje/diagnostics/overlap.py
cje/diagnostics/reward_boundary.py
cje/diagnostics/robust_inference.py
cje/diagnostics/transport.py
cje/diagnostics/weights.py
cje/estimators/README.md
cje/estimators/__init__.py
cje/estimators/base_estimator.py
cje/estimators/calibrated_ips.py
cje/estimators/direct_method.py
cje/estimators/dr_base.py
cje/estimators/mrdr.py
cje/estimators/outcome_models.py
cje/estimators/stacking.py
cje/estimators/tmle.py
cje/interface/README.md
cje/interface/__init__.py
cje/interface/analysis.py
cje/interface/cli.py
cje/interface/config.py
cje/interface/factory.py
cje/interface/hydra_entry.py
cje/interface/mode_detection.py
cje/interface/service.py
cje/py.typed
cje/research.py
cje/teacher_forcing/README.md
cje/teacher_forcing/__init__.py
cje/teacher_forcing/api/__init__.py
cje/teacher_forcing/api/fireworks.py
cje/teacher_forcing/chat.py
cje/teacher_forcing/templates/__init__.py
cje/teacher_forcing/templates/base.py
cje/teacher_forcing/templates/fireworks.py
cje/teacher_forcing/templates/huggingface.py
cje/teacher_forcing/templates/llama.py
cje/tests/README.md
cje_eval-0.2.13.dist-info/METADATA
cje_eval-0.2.13.dist-info/WHEEL
cje_eval-0.2.13.dist-info/entry_points.txt
cje_eval-0.2.13.dist-info/licenses/LICENSE
cje_eval-0.2.13.dist-info/RECORD
