Metadata-Version: 2.4
Name: cje-eval
Version: 0.2.13
Summary: Causal Judge Evaluation - Unbiased LLM evaluation framework
License: MIT
License-File: LICENSE
Keywords: evaluation,llm,causal-inference,off-policy,importance-sampling,doubly-robust
Author: Eddie Landesberg
Author-email: eddie@cimolabs.com
Requires-Python: >=3.9,<3.13
Classifier: Intended Audience :: Science/Research
Classifier: License :: OSI Approved :: MIT License
Classifier: Programming Language :: Python :: 3
Classifier: Programming Language :: Python :: 3.9
Classifier: Programming Language :: Python :: 3.10
Classifier: Programming Language :: Python :: 3.11
Classifier: Programming Language :: Python :: 3.12
Classifier: Topic :: Scientific/Engineering :: Artificial Intelligence
Provides-Extra: all
Provides-Extra: hydra
Provides-Extra: teacher-forcing
Provides-Extra: viz
Requires-Dist: fireworks-ai (>=0.15.0,<0.16.0) ; extra == "teacher-forcing" or extra == "all"
Requires-Dist: hydra-core (>=1.3,<2.0) ; extra == "hydra" or extra == "all"
Requires-Dist: matplotlib (>=3.8,<4.0) ; extra == "viz" or extra == "all"
Requires-Dist: numpy (>=1.26,<2.1)
Requires-Dist: omegaconf (>=2.3,<3.0) ; extra == "hydra" or extra == "all"
Requires-Dist: pandas (>=2.2,<3.0)
Requires-Dist: pydantic (>=2.6,<3.0)
Requires-Dist: python-dotenv (>=1.1.0,<2.0.0)
Requires-Dist: scikit-learn (>=1.4,<2.0)
Requires-Dist: scipy (>=1.11.0,<2.0.0)
Requires-Dist: seaborn (>=0.13.2,<0.14.0) ; extra == "viz" or extra == "all"
Requires-Dist: transformers (>=4.52.2,<5.0.0) ; extra == "teacher-forcing" or extra == "all"
Project-URL: Documentation, https://arxiv.org/abs/2512.11150
Project-URL: Homepage, https://cimolabs.com/cje
Project-URL: Repository, https://github.com/cimo-labs/cje
